sqs_msg_transfer/__init__.py
sqs_msg_transfer/sqs_move_msg.py
sqs_msg_transfer-0.0.1.dist-info/METADATA
sqs_msg_transfer-0.0.1.dist-info/WHEEL
sqs_msg_transfer-0.0.1.dist-info/top_level.txt
sqs_msg_transfer-0.0.1.dist-info/RECORD
