Metadata-Version: 2.1
Name: sqs-msg-transfer
Version: 0.0.1
Summary: A Transfer SQS messages from one Queue to another
Home-page: https://github.com/sathyanarayan/qs_msg_transfer
Author: sathyanarayan
Author-email: sathyanarayan.mec09@gmail.com
License: UNKNOWN
Platform: UNKNOWN
Classifier: Programming Language :: Python :: 3
Classifier: License :: OSI Approved :: MIT License
Classifier: Operating System :: OS Independent
Requires-Python: >=3.6
Requires-Dist: boto3 (>=1.9.236)
